Workbook

Sheet Légende
A1: Prévisionnel : habitat inclusif en Guadeloupe (DMS)
A3: Document de travail. Tous les chiffres sont des HYPOTHÈSES à remplacer ; ils ne sont ni vérifiés ni validés par un expert-comptable.
A5: Comment l'utiliser
A6: 1. Onglet « Hypothèses » : modifie les cellules en bleu (texte bleu). Les cellules jaunes sont les hypothèses clés (AVP, loyer, animateur).
A7: 2. Onglet « Scénarios » : 4 scénarios prêts + une colonne « Mon scénario » à remplir (cellules bleues).
A8: 3. Onglet « Montée en charge » : 6 premiers mois après l'ouverture (nombre d'habitants par mois en bleu).
A9: 4. Onglet « Démarrage et financement » : budget de départ, prêts, remboursements.
A11: Code couleur
A12: Bleu = valeur saisie à modifier · Noir = formule (ne pas écraser) · Vert = lien vers un autre onglet · Jaune = hypothèse clé.
A14: Sources des hypothèses
A15: Loyer de la maison : annonces de location en Guadeloupe (maisons de 4 pièces de 900 à 2 500 €/mois selon la commune).
A16: AVP : plafond national de 10 000 € par an et par habitant ; le Département de la Guadeloupe y consacre 50 000 € en 2026 (enveloppe globale) et finance les travaux jusqu'à 150 000 € par habitat ; le montant par habitant n'est PAS vérifié.
... A23: Les prestations facturées par DMS aux habitants ne sont PAS dans le résultat de l'habitat : elles figurent à part (ligne « Marge DMS potentielle »).

Sheet Hypothèses
A1: Hypothèses
A3: Libellé | B3: Valeur | C3: Unité | D3: Source / commentaire
A4: Loyer de la maison | B4: 1800 | C4: €/mois | D4: Annonces Guadeloupe : maisons de 4 pièces de 900 à 2 500 €
A5: Charges (eau, électricité, internet) | B5: 450 | C5: €/mois | D5: Hypothèse
A6: Entretien et petites réparations | B6: 150 | C6: €/mois | D6: Hypothèse
A7: Assurance (multirisque, responsabilité civile) | B7: 80 | C7: €/mois | D7: Hypothèse
A8: Comptabilité, frais de structure et gestion à distance (voyages, gestionnaire local) | B8: 400 | C8: €/mois | D8: Hypothèse : 100 € de comptabilité + 300 € de gestion à distance
A9: Coût animateur(trice) à temps plein, chargé | B9: 2300 | C9: €/mois | D9: Hypothèse (à vérifier selon convention collective)
A10: Loyer + charges payés par chaque habitant | B10: 750 | C10: €/mois | D10: Hypothèse (hors repas et aide à domicile)
A11: Taux annuel du prêt bancaire | B11: 0.05 | C11: % | D11: Hypothèse
A12: Durée du prêt bancaire | B12: 5 | C12: ans | D12: Hypothèse
A13: Durée du prêt d'honneur | B13: 5 | C13: ans | D13: Prêt d'honneur remboursé sur 3 à 5 ans
A14: Marge de DMS sur ses prestations aux habitants | B14: 0.25 | C14: % | D14: Hypothèse
A15: Achat mensuel de prestations DMS par habitant | B15: 300 | C15: €/mois | D15: Hypothèse ; libre choix de l'habitant
A17: Budget de démarrage
A18: Libellé | B18: Valeur | C18: Unité | D18: Source / commentaire
A19: Dépôt de garantie + premier loyer (en mois de loyer) | B19: 2 | C19: mois | D19: Hypothèse
A20: Mobilier et équipement (4 chambres + espaces communs) | B20: 6000 | C20: € | D20: Hypothèse (4 000 à 8 000 €)
A21: Petites adaptations (barres d'appui, éclairage, douche) | B21: 2500 | C21: € | D21: Hypothèse
A22: Création de la structure dédiée et frais juridiques | B22: 800 | C22: € | D22: Hypothèse
A23: Assurances de la première année (payées d'avance) | B23: 1000 | C23: € | D23: Hypothèse
A24: Communication, recherche d'habitants et séjour sur place (1 mois) | B24: 3500 | C24: € | D24: Hypothèse : billet et logement 2 500 à 4 000 € + communication
A25: Trésorerie de sécurité (en mois de charges) | B25: 3 | C25: mois | D25: Hypothèse
A26: Mois de loyer et charges payés avant l'ouverture | B26: 3 | C26: mois | D26: Hypothèse (bail signé avant l'arrivée des habitants)
A28: Financement
A29: Libellé | B29: Valeur | C29: Unité | D29: Source / commentaire
A30: Prêt d'honneur (Initiative Guadeloupe) | B30: 15000 | C30: € | D30: Montants annoncés : 5 000 à 30 000 € (à confirmer)
A31: Prêt bancaire ou micro-crédit | B31: 8000 | C31: € | D31: Hypothèse ; banques et Adie à vérifier

Sheet Scénarios
A1: Scénarios mensuels (régime de croisière)
A3: Mensuel, en € | B3: Prudent | C3: Cible | D3: Faible occupation | E3: Sans AVP | F3: Mon scénario
A4: Habitants | B4: 4 | C4: 4 | D4: 3 | E4: 4 | F4: 4
A5: AVP par habitant et par an | B5: 3000 | C5: 5000 | D5: 3000 | E5: 0 | F5: 3000
A6: Temps de l'animateur (% d'un temps plein) | B6: 0.5 | C6: 0.7 | D6: 0.5 | E6: 0.5 | F6: 0.5
A7: Loyer + charges par habitant | B7: ='Hypothèses'!$B$10 | C7: ='Hypothèses'!$B$10 | D7: ='Hypothèses'!$B$10 | E7: ='Hypothèses'!$B$10 | F7: 750
A8: Charges
A9: Loyer de la maison | B9: ='Hypothèses'!$B$4 | C9: ='Hypothèses'!$B$4 | D9: ='Hypothèses'!$B$4 | E9: ='Hypothèses'!$B$4 | F9: ='Hypothèses'!$B$4
A10: Charges | B10: ='Hypothèses'!$B$5 | C10: ='Hypothèses'!$B$5 | D10: ='Hypothèses'!$B$5 | E10: ='Hypothèses'!$B$5 | F10: ='Hypothèses'!$B$5
A11: Entretien | B11: ='Hypothèses'!$B$6 | C11: ='Hypothèses'!$B$6 | D11: ='Hypothèses'!$B$6 | E11: ='Hypothèses'!$B$6 | F11: ='Hypothèses'!$B$6
A12: Assurance | B12: ='Hypothèses'!$B$7 | C12: ='Hypothèses'!$B$7 | D12: ='Hypothèses'!$B$7 | E12: ='Hypothèses'!$B$7 | F12: ='Hypothèses'!$B$7
A13: Comptabilité et frais de structure | B13: ='Hypothèses'!$B$8 | C13: ='Hypothèses'!$B$8 | D13: ='Hypothèses'!$B$8 | E13: ='Hypothèses'!$B$8 | F13: ='Hypothèses'!$B$8
A14: Animateur(trice) | B14: ='Hypothèses'!$B$9*B6 | C14: ='Hypothèses'!$B$9*C6 | D14: ='Hypothèses'!$B$9*D6 | E14: ='Hypothèses'!$B$9*E6 | F14: ='Hypothèses'!$B$9*F6
A15: Total charges | B15: =SUM(B9:B14) | C15: =SUM(C9:C14) | D15: =SUM(D9:D14) | E15: =SUM(E9:E14) | F15: =SUM(F9:F14)
A16: Recettes
A17: Recettes AVP | B17: =B4*B5/12 | C17: =C4*C5/12 | D17: =D4*D5/12 | E17: =E4*E5/12 | F17: =F4*F5/12
A18: Recettes loyers des habitants | B18: =B4*B7 | C18: =C4*C7 | D18: =D4*D7 | E18: =E4*E7 | F18: =F4*F7
A19: Total recettes | B19: =B17+B18 | C19: =C17+C18 | D19: =D17+D18 | E19: =E17+E18 | F19: =F17+F18
A20: Résultats
A21: Résultat mensuel | B21: =B19-B15 | C21: =C19-C15 | D21: =D19-D15 | E21: =E19-E15 | F21: =F19-F15
A22: Résultat annuel | B22: =B21*12 | C22: =C21*12 | D22: =D21*12 | E22: =E21*12 | F22: =F21*12
A23: Loyer d'équilibre par habitant (avec AVP) | B23: =IF(B4>0,(B15-B17)/B4,0) | C23: =IF(C4>0,(C15-C17)/C4,0) | D23: =IF(D4>0,(D15-D17)/D4,0) | E23: =IF(E4>0,(E15-E17)/E4,0) | F23: =IF(F4>0,(F15-F17)/F4,0)
A24: Loyer d'équilibre par habitant (sans AVP) | B24: =IF(B4>0,B15/B4,0) | C24: =IF(C4>0,C15/C4,0) | D24: =IF(D4>0,D15/D4,0) | E24: =IF(E4>0,E15/E4,0) | F24: =IF(F4>0,F15/F4,0)
A26: Marge DMS potentielle sur prestations (hors résultat) | B26: =B4*'Hypothèses'!$B$15*'Hypothèses'!$B$14 | C26: =C4*'Hypothèses'!$B$15*'Hypothèses'!$B$14 | D26: =D4*'Hypothèses'!$B$15*'Hypothèses'!$B$14 | E26: =E4*'Hypothèses'!$B$15*'Hypothèses'!$B$14 | F26: =F4*'Hypothèses'!$B$15*'Hypothèses'!$B$14
A27: Résultat mensuel après remboursement du prêt bancaire | B27: =B21-'Démarrage et financement'!$B$19 | C27: =C21-'Démarrage et financement'!$B$19 | D27: =D21-'Démarrage et financement'!$B$19 | E27: =E21-'Démarrage et financement'!$B$19 | F27: =F21-'Démarrage et financement'!$B$19
A29: Lecture : une chambre vide coûte environ le loyer d'équilibre ci-dessus. Sans AVP, le modèle ne tient pas : obtenir la convention avant de signer le bail.

Sheet Montée en charge
A1: Montée en charge : 6 premiers mois après l'ouverture (scénario Prudent)
A3: Mois | B3: Mois 1 | C3: Mois 2 | D3: Mois 3 | E3: Mois 4 | F3: Mois 5 | G3: Mois 6 | H3: Total
A4: Habitants présents | B4: 2 | C4: 3 | D4: 3 | E4: 4 | F4: 4 | G4: 4 | H4: =SUM(B4:G4)
A5: Recettes (AVP + loyers) | B5: =B4*('Scénarios'!$B$5/12+'Scénarios'!$B$7) | C5: =C4*('Scénarios'!$B$5/12+'Scénarios'!$B$7) | D5: =D4*('Scénarios'!$B$5/12+'Scénarios'!$B$7) | E5: =E4*('Scénarios'!$B$5/12+'Scénarios'!$B$7) | F5: =F4*('Scénarios'!$B$5/12+'Scénarios'!$B$7) | G5: =G4*('Scénarios'!$B$5/12+'Scénarios'!$B$7) | H5: =SUM(B5:G5)
A6: Charges | B6: ='Scénarios'!$B$15 | C6: ='Scénarios'!$B$15 | D6: ='Scénarios'!$B$15 | E6: ='Scénarios'!$B$15 | F6: ='Scénarios'!$B$15 | G6: ='Scénarios'!$B$15 | H6: =SUM(B6:G6)
A7: Résultat | B7: =B5-B6 | C7: =C5-C6 | D7: =D5-D6 | E7: =E5-E6 | F7: =F5-F6 | G7: =G5-G6 | H7: =SUM(B7:G7)
A8: Résultat cumulé | B8: =SUM($B$7:B7) | C8: =SUM($B$7:C7) | D8: =SUM($B$7:D7) | E8: =SUM($B$7:E7) | F8: =SUM($B$7:F7) | G8: =SUM($B$7:G7)
A10: À prévoir en plus : loyer et charges de la maison avant l'arrivée des habitants (voir onglet Démarrage et financement).

Sheet Démarrage et financement
A1: Budget de démarrage et financement
A3: Poste | B3: Montant
A4: Dépôt de garantie + premier loyer | B4: ='Hypothèses'!B19*'Hypothèses'!B4
A5: Mobilier et équipement | B5: ='Hypothèses'!B20
A6: Petites adaptations | B6: ='Hypothèses'!B21
A7: Création de la structure dédiée et frais juridiques | B7: ='Hypothèses'!B22
A8: Assurances de la première année | B8: ='Hypothèses'!B23
A9: Communication, recherche d'habitants et séjour sur place | B9: ='Hypothèses'!B24
A10: Trésorerie de sécurité | B10: ='Hypothèses'!B25*'Scénarios'!B15
A11: Total budget de démarrage | B11: =SUM(B4:B10)
A12: Mémo (hors total) : loyer et charges avant l'ouverture | B12: ='Hypothèses'!B26*('Hypothèses'!B4+'Hypothèses'!B5+'Hypothèses'!B6+'Hypothèses'!B7)
A14: Financement
A15: Prêt d'honneur | B15: ='Hypothèses'!B30
A16: Prêt bancaire ou micro-crédit | B16: ='Hypothèses'!B31
A17: Apport personnel nécessaire (total - prêts) | B17: =MAX(0,B11-B15-B16)
A18: Contrôle : financement - besoin (doit être >= 0) | B18: =B15+B16+B17-B11
A19: Remboursement mensuel du prêt bancaire | B19: =IF('Hypothèses'!B31>0,-PMT('Hypothèses'!B11/12,'Hypothèses'!B12*12,'Hypothèses'!B31),0)
A20: Remboursement mensuel du prêt d'honneur (remboursé à titre personnel) | B20: =IF('Hypothèses'!B13>0,B15/('Hypothèses'!B13*12),0)
A22: Lecture : le scénario Prudent ne couvre pas les remboursements. Renforcer le modèle (AVP, loyer, remplissage) avant de s'endetter.
