Workbook

Sheet Hypothèses
A1: Modèle économique — habitat inclusif (Marne)
A2: Les cellules jaunes sont des HYPOTHÈSES ILLUSTRATIVES à remplacer par vos données réelles et par les barèmes du Département. Aucune valeur n'est un chiffre officiel.
A4: Paramètre | B4: Valeur | C4: Unité | D4: Remarque
A5: Nombre d'habitants | B5: 6 | C5: habitants | D5: Fourchette envisagée : 5 à 7
A6: Habitants éligibles à l'AVP | B6: 4 | C6: habitants | D6: 65 ans et plus ou handicap reconnu ; à confirmer auprès du Département
A7: AVP par habitant éligible et par an | B7: 5000 | C7: € | D7: Socle indicatif CNSA cité dans des documents ; fourchette 3 000 à 10 000 €. Barème marnais à confirmer
A8: Loyer mensuel par habitant (hors charges) | B8: 450 | C8: € | D8: Illustratif : à remplacer par le loyer visé / conventionné
A9: Charges mensuelles par habitant | B9: 120 | C9: € | D9: Illustratif : chauffage, eau, électricité, internet
A10: Coût annuel de l'animateur (temps partiel, chargé) | B10: 18000 | C10: € | D10: Illustratif : à calculer selon la convention collective et le temps de travail
A11: Frais de fonctionnement de l'association par an | B11: 4000 | C11: € | D11: Illustratif : assurance, comptabilité, cotisations, formation
A12: Budget annuel d'activités partagées | B12: 1500 | C12: € | D12: Illustratif : repas partagés, sorties, matériel
A13: Participation volontaire des habitants aux activités / mois / habitant | B13: 15 | C13: € | D13: Illustratif : optionnel
A14: Prix d'acquisition + travaux de la maison | B14: 300000 | C14: € | D14: Illustratif : à remplacer
A15: Subvention d'investissement CNSA (via Département) | B15: 0 | C15: € | D15: Plafond 2026 : 150 000 € par habitat, sous réserve de programmation AVP. Mettre 0 tant que non acquis
A16: Autres subventions (Anah, collectivité, fondation) | B16: 0 | C16: € | D16: Mettre 0 tant que non acquis
A17: Apport / fonds propres | B17: 0 | C17: € | D17: Aucun apport à ce stade
A18: Taux du prêt | B18: 0.04 | D18: Illustratif
A19: Durée du prêt | B19: 25 | C19: ans | D19: Illustratif

Sheet Budget annuel
A1: Budget annuel de l'association porteuse (le propriétaire est traité séparément)
A3: Ligne | B3: Montant annuel (€) | C3: Commentaire
A4: RECETTES
A5: AVP (habitants éligibles × montant) | B5: =Hypothèses!$B$6*Hypothèses!$B$7 | C5: Perçue par l'association si le projet est programmé par le Département
A6: Participations volontaires des habitants | B6: =Hypothèses!$B$5*Hypothèses!$B$13*12 | C6: Optionnel
A7: Total recettes | B7: =B5+B6
A8: DÉPENSES
A9: Animateur (chargé) | B9: =Hypothèses!$B$10
A10: Fonctionnement de l'association | B10: =Hypothèses!$B$11
A11: Activités partagées | B11: =Hypothèses!$B$12
A12: Total dépenses | B12: =B9+B10+B11
A13: RÉSULTAT (recettes − dépenses) | B13: =B7-B12 | C13: Doit être ≥ 0 pour être soutenable
A14: Couverture des dépenses par l'AVP seule | B14: =IF(B12=0,0,B5/B12) | C14: 100 % = l'AVP finance toute l'animation

Sheet Scénarios éligibles
A1: Sensibilité : nombre d'habitants éligibles à l'AVP (autres hypothèses inchangées)
A3: Habitants éligibles | B3: AVP annuelle (€) | C3: Dépenses annuelles (€) | D3: Résultat (€) | E3: Couverture AVP
A4: 0 | B4: =A4*Hypothèses!$B$7 | C4: ='Budget annuel'!$B$12 | D4: =B4+'Budget annuel'!$B$6-C4 | E4: =IF(C4=0,0,B4/C4)
A5: 1 | B5: =A5*Hypothèses!$B$7 | C5: ='Budget annuel'!$B$12 | D5: =B5+'Budget annuel'!$B$6-C5 | E5: =IF(C5=0,0,B5/C5)
A6: 2 | B6: =A6*Hypothèses!$B$7 | C6: ='Budget annuel'!$B$12 | D6: =B6+'Budget annuel'!$B$6-C6 | E6: =IF(C6=0,0,B6/C6)
A7: 3 | B7: =A7*Hypothèses!$B$7 | C7: ='Budget annuel'!$B$12 | D7: =B7+'Budget annuel'!$B$6-C7 | E7: =IF(C7=0,0,B7/C7)
A8: 4 | B8: =A8*Hypothèses!$B$7 | C8: ='Budget annuel'!$B$12 | D8: =B8+'Budget annuel'!$B$6-C8 | E8: =IF(C8=0,0,B8/C8)
A9: 5 | B9: =A9*Hypothèses!$B$7 | C9: ='Budget annuel'!$B$12 | D9: =B9+'Budget annuel'!$B$6-C9 | E9: =IF(C9=0,0,B9/C9)
A10: 6 | B10: =A10*Hypothèses!$B$7 | C10: ='Budget annuel'!$B$12 | D10: =B10+'Budget annuel'!$B$6-C10 | E10: =IF(C10=0,0,B10/C10)
A11: 7 | B11: =A11*Hypothèses!$B$7 | C11: ='Budget annuel'!$B$12 | D11: =B11+'Budget annuel'!$B$6-C11 | E11: =IF(C11=0,0,B11/C11)
A13: Lecture : au-delà d'une couverture de 100 %, l'AVP finance toute l'animation. Le tableau suppose le montant d'AVP par éligible de l'onglet Hypothèses.

Sheet Investissement
A1: Plan de financement de l'immobilier (côté propriétaire)
A3: Ligne | B3: Montant (€) | C3: Commentaire
A4: Besoin total (acquisition + travaux) | B4: =Hypothèses!$B$14
A5: Subvention CNSA via le Département | B5: =Hypothèses!$B$15 | C5: Plafond 2026 : 150 000 € par habitat ; non acquis tant que le projet n'est pas programmé
A6: Autres subventions | B6: =Hypothèses!$B$16
A7: Apport / fonds propres | B7: =Hypothèses!$B$17
A8: Emprunt à financer | B8: =B4-B5-B6-B7
A9: Mensualité du prêt (estimation) | B9: =IF(B8<=0,0,PMT(Hypothèses!$B$18/12,Hypothèses!$B$19*12,-B8)) | C9: Formule PMT, hors assurance et frais
A10: Loyers perçus par an (tous habitants) | B10: =Hypothèses!$B$5*Hypothèses!$B$8*12 | C10: Loyer hors charges
A11: Mensualités annuelles | B11: =B9*12
A12: Écart loyers − mensualités | B12: =B10-B11 | C12: Doit couvrir aussi taxe foncière, entretien, vacance : non comptés ici
